pylightdmx/__init__.py
pylightdmx/fixtures.py
pylightdmx/rigs.py
pylightdmx-1.0.2.dist-info/METADATA
pylightdmx-1.0.2.dist-info/RECORD
pylightdmx-1.0.2.dist-info/WHEEL
pylightdmx-1.0.2.dist-info/top_level.txt
